{
  "episode": 80,
  "timestamp": "2025-09-16T01:37:49.026223",
  "performance": {
    "episode": 79,
    "reward": -7.000000000000568,
    "episode_length": 360,
    "loss": 3.277847722172737,
    "learning_rate": 0.0002,
    "mcts_simulations": 15,
    "c_puct": 1.25,
    "temperature": 1.0,
    "trades": 15,
    "win_rate": 0.3333333333333333,
    "avg_pips": -30.09333333333321,
    "total_pips": -451.39999999999816,
    "total_pnl": -451.39999999999816,
    "env_reward": -7.000000000000568,
    "max_drawdown": 200.7999999999995,
    "sqn": 0.0,
    "sqn_classification": "Poor System",
    "sqn_confidence": "Insufficient Data",
    "expectancy_r": 0.0,
    "std_dev_r": 1.4638501094227998,
    "timestamp": "2025-09-16T01:37:49.025862",
    "duration_seconds": 25.609118
  },
  "config": {
    "agent_type": "swt_muzero",
    "training_parameters": "standard"
  }
}